// class version 65.65535 (-65471)
// access flags 0x21
// signature Ljava/lang/Object;Larb/functions/Function<Larb/Integer;Larb/Real;>;
// declaration: F implements arb.functions.Function<arb.Integer, arb.Real>
public class F implements arb/functions/Function {

  // access flags 0x2
  private Z isInitialized

  // access flags 0x0
  Larb/Integer; c1

  // access flags 0x1
  public Larb/Real; α

  // access flags 0x1
  public Larb/Real; β

  // access flags 0x1
  public Larb/Real; ℝ1

  // access flags 0x1
  public Larb/Integer; ℤ1

  // access flags 0x1
  public Larb/Real; ℝ2

  // access flags 0x1
  public Larb/Real; ℝ3

  // access flags 0x1
  public Larb/Real; ℝ4

  // access flags 0x11
  public final LC; C

  // access flags 0x1
  public evaluate(Ljava/lang/Object;IILjava/lang/Object;)Ljava/lang/Object;
   L0
    ALOAD 0
    GETFIELD F.isInitialized : Z
    IFNE L1
    ALOAD 0
    INVOKEVIRTUAL F.initialize ()V
   L1
   FRAME SAME
    ALOAD 0
    GETFIELD F.C : LC;
    ALOAD 0
    GETFIELD F.ℝ1 : Larb/Real;
    ALOAD 1
    CHECKCAST arb/Integer
    ALOAD 0
    GETFIELD F.c1 : Larb/Integer;
    ILOAD 3
    ALOAD 0
    GETFIELD F.ℤ1 : Larb/Integer;
    INVOKEVIRTUAL arb/Integer.sub (Larb/Integer;ILarb/Integer;)Larb/Integer;
    INVOKEVIRTUAL arb/Real.set (Larb/Integer;)Larb/Real;
    ILOAD 2
    ILOAD 3
    ALOAD 0
    GETFIELD F.ℝ2 : Larb/Real;
    INVOKEINTERFACE arb/functions/real/RealFunction.evaluate (Ljava/lang/Object;IILjava/lang/Object;)Ljava/lang/Object; (itf)
    CHECKCAST arb/Real
   L2
   FRAME SAME1 arb/Real
    ALOAD 0
    GETFIELD F.C : LC;
    ALOAD 0
    GETFIELD F.ℝ3 : Larb/Real;
    ALOAD 1
    CHECKCAST arb/Integer
    INVOKEVIRTUAL arb/Real.set (Larb/Integer;)Larb/Real;
    ILOAD 2
    ILOAD 3
    ALOAD 0
    GETFIELD F.ℝ4 : Larb/Real;
    INVOKEINTERFACE arb/functions/real/RealFunction.evaluate (Ljava/lang/Object;IILjava/lang/Object;)Ljava/lang/Object; (itf)
    CHECKCAST arb/Real
   L3
   FRAME SAME1 arb/Real
    ILOAD 3
    ALOAD 4
    CHECKCAST arb/Real
    INVOKEVIRTUAL arb/Real.mul (Larb/Real;ILarb/Real;)Larb/Real;
    ARETURN
   L4
    LOCALVARIABLE this LF; L0 L4 0
    LOCALVARIABLE in Larb/Integer; L0 L4 1
    LOCALVARIABLE order I L0 L4 2
    LOCALVARIABLE bits I L0 L4 3
    LOCALVARIABLE result Larb/Real; L0 L4 4
    MAXSTACK = 10
    MAXLOCALS = 10
