Classfile /home/crow/git/arb4j/target/classes/arb/functions/real/factorℝ1.class
  Last modified Mar 17, 2024; size 3361 bytes
  SHA-256 checksum 0b260c589146ed05d0ac3a46592474193de5add6c27cd86d8c0426d45a6996b0
  Compiled from "factorℝ1.java"
[32mpublic class arb.functions.real.factorℝ1 extends java.lang.Object [36mimplements[m arb.functions.Function<arb.Integer, arb.Real>[m
  minor version: 65535
  major version: 65
  flags: (0x0021) ACC_PUBLIC, ACC_SUPER
  this_class: #1                          [31m// arb/functions/real/factorℝ1[m
  super_class: #3                         [31m// java/lang/Object[m
  interfaces: 1, fields: 21, methods: 5, attributes: 2
Constant pool:
    #1 = Class              #2            [31m// arb/functions/real/factorℝ1[m
    #2 = Utf8               arb/functions/real/factorℝ1
    #3 = Class              #4            [31m// java/lang/Object[m
    #4 = Utf8               java/lang/Object
    #5 = Class              #6            [31m// arb/functions/Function[m
    #6 = Utf8               arb/functions/Function
    #7 = Utf8               isInitialized
    #8 = Utf8               Z
    #9 = Utf8               c1
   #10 = Utf8               Larb/Integer;
   #11 = Utf8               z
   #12 = Utf8               Larb/Real;
   #13 = Utf8               p
   #14 = Utf8               q
   #15 = Utf8               α
   #16 = Utf8               β
   #17 = Utf8               N
   #18 = Utf8               ℝ1
   #19 = Utf8               valueℝ2
   #20 = Utf8               k
   #21 = Utf8               prodℝ1
   #22 = Utf8               endIndexℤ1
   #23 = Utf8               ℝ2
   #24 = Utf8               ℤ1
   #25 = Utf8               valueℝ3
   #26 = Utf8               prodℝ2
   #27 = Utf8               endIndexℤ2
   #28 = Utf8               ℝ3
   #29 = Utf8               factorℝ2
   #30 = Utf8               Larb/functions/real/factorℝ2;
   #31 = Utf8               factorℝ3
   #32 = Utf8               Larb/functions/real/factorℝ3;
   #33 = Utf8               evaluate
   #34 = Utf8               (Larb/Integer;IILarb/Real;)Larb/Real;
   #35 = Utf8               Code
   #36 = Fieldref           #1.#37        [31m// arb/functions/real/factorℝ1.isInitialized:Z[m
   #37 = NameAndType        #7:#8         [31m// isInitialized:Z[m
   #38 = Methodref          #1.#39        [31m// arb/functions/real/factorℝ1.initialize:()V[m
   #39 = NameAndType        #40:#41       [31m// initialize:()V[m
   #40 = Utf8               initialize
   #41 = Utf8               ()V
   #42 = Fieldref           #1.#43        [31m// arb/functions/real/factorℝ1.z:Larb/Real;[m
   #43 = NameAndType        #11:#12       [31m// z:Larb/Real;[m
   #44 = Fieldref           #1.#45        [31m// arb/functions/real/factorℝ1.ℝ1:Larb/Real;[m
   #45 = NameAndType        #18:#12       [31m// ℝ1:Larb/Real;[m
   #46 = Methodref          #47.#49       [31m// arb/Real.pow:(Larb/Integer;ILarb/Real;)Larb/Real;[m
   #47 = Class              #48           [31m// arb/Real[m
   #48 = Utf8               arb/Real
   #49 = NameAndType        #50:#51       [31m// pow:(Larb/Integer;ILarb/Real;)Larb/Real;[m
   #50 = Utf8               pow
   #51 = Utf8               (Larb/Integer;ILarb/Real;)Larb/Real;
   #52 = Fieldref           #1.#53        [31m// arb/functions/real/factorℝ1.factorℝ2:Larb/functions/real/factorℝ2;[m
   #53 = NameAndType        #29:#30       [31m// factorℝ2:Larb/functions/real/factorℝ2;[m
   #54 = Fieldref           #55.#57       [31m// arb/functions/real/factorℝ2.n:Larb/Integer;[m
   #55 = Class              #56           [31m// arb/functions/real/factorℝ2[m
   #56 = Utf8               arb/functions/real/factorℝ2
   #57 = NameAndType        #58:#10       [31m// n:Larb/Integer;[m
   #58 = Utf8               n
   #59 = Fieldref           #1.#60        [31m// arb/functions/real/factorℝ1.prodℝ1:Larb/Real;[m
   #60 = NameAndType        #21:#12       [31m// prodℝ1:Larb/Real;[m
   #61 = Methodref          #47.#62       [31m// arb/Real.multiplicativeIdentity:()Larb/Real;[m
   #62 = NameAndType        #63:#64       [31m// multiplicativeIdentity:()Larb/Real;[m
   #63 = Utf8               multiplicativeIdentity
   #64 = Utf8               ()Larb/Real;
   #65 = Fieldref           #1.#66        [31m// arb/functions/real/factorℝ1.k:Larb/Integer;[m
   #66 = NameAndType        #20:#10       [31m// k:Larb/Integer;[m
   #67 = Fieldref           #1.#68        [31m// arb/functions/real/factorℝ1.c1:Larb/Integer;[m
   #68 = NameAndType        #9:#10        [31m// c1:Larb/Integer;[m
   #69 = Methodref          #70.#72       [31m// arb/Integer.set:(Larb/Integer;)Larb/Integer;[m
   #70 = Class              #71           [31m// arb/Integer[m
   #71 = Utf8               arb/Integer
   #72 = NameAndType        #73:#74       [31m// set:(Larb/Integer;)Larb/Integer;[m
   #73 = Utf8               set
   #74 = Utf8               (Larb/Integer;)Larb/Integer;
   #75 = Fieldref           #1.#76        [31m// arb/functions/real/factorℝ1.endIndexℤ1:Larb/Integer;[m
   #76 = NameAndType        #22:#10       [31m// endIndexℤ1:Larb/Integer;[m
   #77 = Fieldref           #1.#78        [31m// arb/functions/real/factorℝ1.p:Larb/Integer;[m
   #78 = NameAndType        #13:#10       [31m// p:Larb/Integer;[m
   #79 = Fieldref           #1.#80        [31m// arb/functions/real/factorℝ1.valueℝ2:Larb/Real;[m
   #80 = NameAndType        #19:#12       [31m// valueℝ2:Larb/Real;[m
   #81 = Methodref          #55.#82       [31m// arb/functions/real/factorℝ2.evaluate:(Ljava/lang/Object;ILjava/lang/Object;)Ljava/lang/Object;[m
   #82 = NameAndType        #33:#83       [31m// evaluate:(Ljava/lang/Object;ILjava/lang/Object;)Ljava/lang/Object;[m
   #83 = Utf8               (Ljava/lang/Object;ILjava/lang/Object;)Ljava/lang/Object;
   #84 = Methodref          #47.#85       [31m// arb/Real.mul:(Larb/Real;I)Larb/Real;[m
   #85 = NameAndType        #86:#87       [31m// mul:(Larb/Real;I)Larb/Real;[m
   #86 = Utf8               mul
   #87 = Utf8               (Larb/Real;I)Larb/Real;
   #88 = Methodref          #70.#89       [31m// arb/Integer.increment:()Larb/Integer;[m
   #89 = NameAndType        #90:#91       [31m// increment:()Larb/Integer;[m
   #90 = Utf8               increment
   #91 = Utf8               ()Larb/Integer;
   #92 = Methodref          #70.#93       [31m// arb/Integer.compareTo:(Larb/Integer;)I[m
   #93 = NameAndType        #94:#95       [31m// compareTo:(Larb/Integer;)I[m
   #94 = Utf8               compareTo
   #95 = Utf8               (Larb/Integer;)I
   #96 = Fieldref           #1.#97        [31m// arb/functions/real/factorℝ1.ℝ2:Larb/Real;[m
   #97 = NameAndType        #23:#12       [31m// ℝ2:Larb/Real;[m
   #98 = Methodref          #47.#99       [31m// arb/Real.mul:(Larb/Real;ILarb/Real;)Larb/Real;[m
   #99 = NameAndType        #86:#100      [31m// mul:(Larb/Real;ILarb/Real;)Larb/Real;[m
  #100 = Utf8               (Larb/Real;ILarb/Real;)Larb/Real;
  #101 = Fieldref           #1.#102       [31m// arb/functions/real/factorℝ1.ℤ1:Larb/Integer;[m
  #102 = NameAndType        #24:#10       [31m// ℤ1:Larb/Integer;[m
  #103 = Methodref          #70.#104      [31m// arb/Integer.factorial:(ILarb/Integer;)Larb/Integer;[m
  #104 = NameAndType        #105:#106     [31m// factorial:(ILarb/Integer;)Larb/Integer;[m
  #105 = Utf8               factorial
  #106 = Utf8               (ILarb/Integer;)Larb/Integer;
  #107 = Fieldref           #1.#108       [31m// arb/functions/real/factorℝ1.factorℝ3:Larb/functions/real/factorℝ3;[m
  #108 = NameAndType        #31:#32       [31m// factorℝ3:Larb/functions/real/factorℝ3;[m
  #109 = Fieldref           #110.#57      [31m// arb/functions/real/factorℝ3.n:Larb/Integer;[m
  #110 = Class              #111          [31m// arb/functions/real/factorℝ3[m
  #111 = Utf8               arb/functions/real/factorℝ3
  #112 = Fieldref           #1.#113       [31m// arb/functions/real/factorℝ1.prodℝ2:Larb/Real;[m
  #113 = NameAndType        #26:#12       [31m// prodℝ2:Larb/Real;[m
  #114 = Fieldref           #1.#115       [31m// arb/functions/real/factorℝ1.endIndexℤ2:Larb/Integer;[m
  #115 = NameAndType        #27:#10       [31m// endIndexℤ2:Larb/Integer;[m
  #116 = Fieldref           #1.#117       [31m// arb/functions/real/factorℝ1.q:Larb/Integer;[m
  #117 = NameAndType        #14:#10       [31m// q:Larb/Integer;[m
  #118 = Fieldref           #1.#119       [31m// arb/functions/real/factorℝ1.valueℝ3:Larb/Real;[m
  #119 = NameAndType        #25:#12       [31m// valueℝ3:Larb/Real;[m
  #120 = Methodref          #110.#82      [31m// arb/functions/real/factorℝ3.evaluate:(Ljava/lang/Object;ILjava/lang/Object;)Ljava/lang/Object;[m
  #121 = Fieldref           #1.#122       [31m// arb/functions/real/factorℝ1.ℝ3:Larb/Real;[m
  #122 = NameAndType        #28:#12       [31m// ℝ3:Larb/Real;[m
  #123 = Methodref          #70.#99       [31m// arb/Integer.mul:(Larb/Real;ILarb/Real;)Larb/Real;[m
  #124 = Methodref          #47.#125      [31m// arb/Real.div:(Larb/Real;ILarb/Real;)Larb/Real;[m
  #125 = NameAndType        #126:#100     [31m// div:(Larb/Real;ILarb/Real;)Larb/Real;[m
  #126 = Utf8               div
  #127 = Utf8               LineNumberTable
  #128 = Utf8               LocalVariableTable
  #129 = Utf8               this
  #130 = Utf8               Larb/functions/real/factorℝ1;
  #131 = Utf8               in
  #132 = Utf8               order
  #133 = Utf8               I
  #134 = Utf8               bits
  #135 = Utf8               result
  #136 = Utf8               var10000
  #137 = Utf8               var10001
  #138 = Utf8               StackMapTable
  #139 = Utf8               <init>
  #140 = Methodref          #3.#141       [31m// java/lang/Object."<init>":()V[m
  #141 = NameAndType        #139:#41      [31m// "<init>":()V[m
  #142 = Methodref          #55.#141      [31m// arb/functions/real/factorℝ2."<init>":()V[m
  #143 = Methodref          #110.#141     [31m// arb/functions/real/factorℝ3."<init>":()V[m
  #144 = String             #145          [31m// 1[m
  #145 = Utf8               1
  #146 = Methodref          #70.#147      [31m// arb/Integer."<init>":(Ljava/lang/String;)V[m
  #147 = NameAndType        #139:#148     [31m// "<init>":(Ljava/lang/String;)V[m
  #148 = Utf8               (Ljava/lang/String;)V
  #149 = Methodref          #47.#141      [31m// arb/Real."<init>":()V[m
  #150 = Methodref          #70.#141      [31m// arb/Integer."<init>":()V[m
  #151 = Class              #152          [31m// java/lang/AssertionError[m
  #152 = Utf8               java/lang/AssertionError
  #153 = String             #154          [31m// Already initialized[m
  #154 = Utf8               Already initialized
  #155 = Methodref          #151.#156     [31m// java/lang/AssertionError."<init>":(Ljava/lang/Object;)V[m
  #156 = NameAndType        #139:#157     [31m// "<init>":(Ljava/lang/Object;)V[m
  #157 = Utf8               (Ljava/lang/Object;)V
  #158 = String             #159          [31m// p is null[m
  #159 = Utf8               p is null
  #160 = String             #161          [31m// q is null[m
  #161 = Utf8               q is null
  #162 = Fieldref           #55.#78       [31m// arb/functions/real/factorℝ2.p:Larb/Integer;[m
  #163 = Fieldref           #55.#117      [31m// arb/functions/real/factorℝ2.q:Larb/Integer;[m
  #164 = Fieldref           #1.#165       [31m// arb/functions/real/factorℝ1.α:Larb/Real;[m
  #165 = NameAndType        #15:#12       [31m// α:Larb/Real;[m
  #166 = Fieldref           #55.#165      [31m// arb/functions/real/factorℝ2.α:Larb/Real;[m
  #167 = Fieldref           #1.#168       [31m// arb/functions/real/factorℝ1.β:Larb/Real;[m
  #168 = NameAndType        #16:#12       [31m// β:Larb/Real;[m
  #169 = Fieldref           #55.#168      [31m// arb/functions/real/factorℝ2.β:Larb/Real;[m
  #170 = Fieldref           #1.#171       [31m// arb/functions/real/factorℝ1.N:Larb/Integer;[m
  #171 = NameAndType        #17:#10       [31m// N:Larb/Integer;[m
  #172 = Fieldref           #55.#171      [31m// arb/functions/real/factorℝ2.N:Larb/Integer;[m
  #173 = Fieldref           #110.#78      [31m// arb/functions/real/factorℝ3.p:Larb/Integer;[m
  #174 = Fieldref           #110.#117     [31m// arb/functions/real/factorℝ3.q:Larb/Integer;[m
  #175 = Fieldref           #110.#165     [31m// arb/functions/real/factorℝ3.α:Larb/Real;[m
  #176 = Fieldref           #110.#168     [31m// arb/functions/real/factorℝ3.β:Larb/Real;[m
  #177 = Fieldref           #110.#171     [31m// arb/functions/real/factorℝ3.N:Larb/Integer;[m
  #178 = Utf8               close
  #179 = Methodref          #70.#180      [31m// arb/Integer.close:()V[m
  #180 = NameAndType        #178:#41      [31m// close:()V[m
  #181 = Methodref          #47.#180      [31m// arb/Real.close:()V[m
  #182 = Utf8               (Ljava/lang/Object;IILjava/lang/Object;)Ljava/lang/Object;
  #183 = Methodref          #1.#184       [31m// arb/functions/real/factorℝ1.evaluate:(Larb/Integer;IILarb/Real;)Larb/Real;[m
  #184 = NameAndType        #33:#34       [31m// evaluate:(Larb/Integer;IILarb/Real;)Larb/Real;[m
  #185 = Utf8               SourceFile
  #186 = Utf8               factorℝ1.java
  #187 = Utf8               Signature
  #188 = Utf8               Ljava/lang/Object;Larb/functions/Function<Larb/Integer;Larb/Real;>;
{
  arb.Integer c1;
    descriptor: Larb/Integer;
    flags: (0x0000)

[32m  public arb.Real z;[m
    descriptor: Larb/Real;
    flags: (0x0001) ACC_PUBLIC

[32m  public arb.Integer p;[m
    descriptor: Larb/Integer;
    flags: (0x0001) ACC_PUBLIC

[32m  public arb.Integer q;[m
    descriptor: Larb/Integer;
    flags: (0x0001) ACC_PUBLIC

[32m  public arb.Real α;[m
    descriptor: Larb/Real;
    flags: (0x0001) ACC_PUBLIC

[32m  public arb.Real β;[m
    descriptor: Larb/Real;
    flags: (0x0001) ACC_PUBLIC

[32m  public arb.Integer N;[m
    descriptor: Larb/Integer;
    flags: (0x0001) ACC_PUBLIC

[32m  public arb.Real ℝ1;[m
    descriptor: Larb/Real;
    flags: (0x0001) ACC_PUBLIC

[32m  public arb.Real valueℝ2;[m
    descriptor: Larb/Real;
    flags: (0x0001) ACC_PUBLIC

[32m  public arb.Integer k;[m
    descriptor: Larb/Integer;
    flags: (0x0001) ACC_PUBLIC

[32m  public arb.Real prodℝ1;[m
    descriptor: Larb/Real;
    flags: (0x0001) ACC_PUBLIC

[32m  public arb.Integer endIndexℤ1;[m
    descriptor: Larb/Integer;
    flags: (0x0001) ACC_PUBLIC

[32m  public arb.Real ℝ2;[m
    descriptor: Larb/Real;
    flags: (0x0001) ACC_PUBLIC

[32m  public arb.Integer ℤ1;[m
    descriptor: Larb/Integer;
    flags: (0x0001) ACC_PUBLIC

[32m  public arb.Real valueℝ3;[m
    descriptor: Larb/Real;
    flags: (0x0001) ACC_PUBLIC

[32m  public arb.Real prodℝ2;[m
    descriptor: Larb/Real;
    flags: (0x0001) ACC_PUBLIC

[32m  public arb.Integer endIndexℤ2;[m
    descriptor: Larb/Integer;
    flags: (0x0001) ACC_PUBLIC

[32m  public arb.Real ℝ3;[m
    descriptor: Larb/Real;
    flags: (0x0001) ACC_PUBLIC

[32m  public final arb.functions.real.factorℝ2 factorℝ2;[m
    descriptor: Larb/functions/real/factorℝ2;
    flags: (0x0011) ACC_PUBLIC, ACC_FINAL

[32m  public final arb.functions.real.factorℝ3 factorℝ3;[m
    descriptor: Larb/functions/real/factorℝ3;
    flags: (0x0011) ACC_PUBLIC, ACC_FINAL

[32m  public arb.Real evaluate(arb.Integer, int, int, arb.Real);[m
    descriptor: (Larb/Integer;IILarb/Real;)Larb/Real;
    flags: (0x0001) ACC_PUBLIC
[36m    Code:[m
      stack=5, locals=7, args_size=5
[33m         0:[m aload_0
[33m         1:[m getfield      #36                 [31m// Field isInitialized:Z[m
[33m         4:[m ifne          11
[33m         7:[m aload_0
[33m         8:[m invokevirtual #38                 [31m// Method initialize:()V[m
[33m        11:[m aload_0
[33m        12:[m getfield      #42                 [31m// Field z:Larb/Real;[m
[33m        15:[m aload_1
[33m        16:[m iload_3
[33m        17:[m aload_0
[33m        18:[m getfield      #44                 [31m// Field ℝ1:Larb/Real;[m
[33m        21:[m invokevirtual #46                 [31m// Method arb/Real.pow:(Larb/Integer;ILarb/Real;)Larb/Real;[m
[33m        24:[m astore        5
[33m        26:[m aload_0
[33m        27:[m getfield      #52                 [31m// Field factorℝ2:Larb/functions/real/factorℝ2;[m
[33m        30:[m aload_1
[33m        31:[m putfield      #54                 [31m// Field arb/functions/real/factorℝ2.n:Larb/Integer;[m
[33m        34:[m aload_0
[33m        35:[m getfield      #59                 [31m// Field prodℝ1:Larb/Real;[m
[33m        38:[m invokevirtual #61                 [31m// Method arb/Real.multiplicativeIdentity:()Larb/Real;[m
[33m        41:[m pop
[33m        42:[m aload_0
[33m        43:[m getfield      #65                 [31m// Field k:Larb/Integer;[m
[33m        46:[m aload_0
[33m        47:[m getfield      #67                 [31m// Field c1:Larb/Integer;[m
[33m        50:[m invokevirtual #69                 [31m// Method arb/Integer.set:(Larb/Integer;)Larb/Integer;[m
[33m        53:[m pop
[33m        54:[m aload_0
[33m        55:[m getfield      #75                 [31m// Field endIndexℤ1:Larb/Integer;[m
[33m        58:[m aload_0
[33m        59:[m getfield      #77                 [31m// Field p:Larb/Integer;[m
[33m        62:[m invokevirtual #69                 [31m// Method arb/Integer.set:(Larb/Integer;)Larb/Integer;[m
[33m        65:[m pop
[33m        66:[m aload_0
[33m        67:[m getfield      #59                 [31m// Field prodℝ1:Larb/Real;[m
[33m        70:[m aload_0
[33m        71:[m getfield      #52                 [31m// Field factorℝ2:Larb/functions/real/factorℝ2;[m
[33m        74:[m aload_0
[33m        75:[m getfield      #65                 [31m// Field k:Larb/Integer;[m
[33m        78:[m iload_3
[33m        79:[m aload_0
[33m        80:[m getfield      #79                 [31m// Field valueℝ2:Larb/Real;[m
[33m        83:[m invokevirtual #81                 [31m// Method arb/functions/real/factorℝ2.evaluate:(Ljava/lang/Object;ILjava/lang/Object;)Ljava/lang/Object;[m
[33m        86:[m checkcast     #47                 [31m// class arb/Real[m
[33m        89:[m iload_3
[33m        90:[m invokevirtual #84                 [31m// Method arb/Real.mul:(Larb/Real;I)Larb/Real;[m
[33m        93:[m pop
[33m        94:[m aload_0
[33m        95:[m getfield      #65                 [31m// Field k:Larb/Integer;[m
[33m        98:[m invokevirtual #88                 [31m// Method arb/Integer.increment:()Larb/Integer;[m
[33m       101:[m aload_0
[33m       102:[m getfield      #75                 [31m// Field endIndexℤ1:Larb/Integer;[m
[33m       105:[m invokevirtual #92                 [31m// Method arb/Integer.compareTo:(Larb/Integer;)I[m
[33m       108:[m ifle          66
[33m       111:[m aload         5
[33m       113:[m aload_0
[33m       114:[m getfield      #59                 [31m// Field prodℝ1:Larb/Real;[m
[33m       117:[m iload_3
[33m       118:[m aload_0
[33m       119:[m getfield      #96                 [31m// Field ℝ2:Larb/Real;[m
[33m       122:[m invokevirtual #98                 [31m// Method arb/Real.mul:(Larb/Real;ILarb/Real;)Larb/Real;[m
[33m       125:[m astore        5
[33m       127:[m aload_1
[33m       128:[m iload_3
[33m       129:[m aload_0
[33m       130:[m getfield      #101                [31m// Field ℤ1:Larb/Integer;[m
[33m       133:[m invokevirtual #103                [31m// Method arb/Integer.factorial:(ILarb/Integer;)Larb/Integer;[m
[33m       136:[m astore        6
[33m       138:[m aload_0
[33m       139:[m getfield      #107                [31m// Field factorℝ3:Larb/functions/real/factorℝ3;[m
[33m       142:[m aload_1
[33m       143:[m putfield      #109                [31m// Field arb/functions/real/factorℝ3.n:Larb/Integer;[m
[33m       146:[m aload_0
[33m       147:[m getfield      #112                [31m// Field prodℝ2:Larb/Real;[m
[33m       150:[m invokevirtual #61                 [31m// Method arb/Real.multiplicativeIdentity:()Larb/Real;[m
[33m       153:[m pop
[33m       154:[m aload_0
[33m       155:[m getfield      #65                 [31m// Field k:Larb/Integer;[m
[33m       158:[m aload_0
[33m       159:[m getfield      #67                 [31m// Field c1:Larb/Integer;[m
[33m       162:[m invokevirtual #69                 [31m// Method arb/Integer.set:(Larb/Integer;)Larb/Integer;[m
[33m       165:[m pop
[33m       166:[m aload_0
[33m       167:[m getfield      #114                [31m// Field endIndexℤ2:Larb/Integer;[m
[33m       170:[m aload_0
[33m       171:[m getfield      #116                [31m// Field q:Larb/Integer;[m
[33m       174:[m invokevirtual #69                 [31m// Method arb/Integer.set:(Larb/Integer;)Larb/Integer;[m
[33m       177:[m pop
[33m       178:[m aload_0
[33m       179:[m getfield      #112                [31m// Field prodℝ2:Larb/Real;[m
[33m       182:[m aload_0
[33m       183:[m getfield      #107                [31m// Field factorℝ3:Larb/functions/real/factorℝ3;[m
[33m       186:[m aload_0
[33m       187:[m getfield      #65                 [31m// Field k:Larb/Integer;[m
[33m       190:[m iload_3
[33m       191:[m aload_0
[33m       192:[m getfield      #118                [31m// Field valueℝ3:Larb/Real;[m
[33m       195:[m invokevirtual #120                [31m// Method arb/functions/real/factorℝ3.evaluate:(Ljava/lang/Object;ILjava/lang/Object;)Ljava/lang/Object;[m
[33m       198:[m checkcast     #47                 [31m// class arb/Real[m
[33m       201:[m iload_3
[33m       202:[m invokevirtual #84                 [31m// Method arb/Real.mul:(Larb/Real;I)Larb/Real;[m
[33m       205:[m pop
[33m       206:[m aload_0
[33m       207:[m getfield      #65                 [31m// Field k:Larb/Integer;[m
[33m       210:[m invokevirtual #88                 [31m// Method arb/Integer.increment:()Larb/Integer;[m
[33m       213:[m aload_0
[33m       214:[m getfield      #114                [31m// Field endIndexℤ2:Larb/Integer;[m
[33m       217:[m invokevirtual #92                 [31m// Method arb/Integer.compareTo:(Larb/Integer;)I[m
[33m       220:[m ifle          178
[33m       223:[m aload         5
[33m       225:[m aload         6
[33m       227:[m aload_0
[33m       228:[m getfield      #112                [31m// Field prodℝ2:Larb/Real;[m
[33m       231:[m iload_3
[33m       232:[m aload_0
[33m       233:[m getfield      #121                [31m// Field ℝ3:Larb/Real;[m
[33m       236:[m invokevirtual #123                [31m// Method arb/Integer.mul:(Larb/Real;ILarb/Real;)Larb/Real;[m
[33m       239:[m iload_3
[33m       240:[m aload         4
[33m       242:[m invokevirtual #124                [31m// Method arb/Real.div:(Larb/Real;ILarb/Real;)Larb/Real;[m
[33m       245:[m areturn
      LineNumberTable:
        line 34: 0
        line 36: 7
        line 39: 11
        line 40: 26
        line 41: 34
        line 42: 42
        line 43: 54
        line 47: 66
        line 49: 94
        line 45: 108
        line 51: 111
        line 52: 127
        line 53: 138
        line 54: 146
        line 55: 154
        line 56: 166
        line 60: 178
        line 62: 206
        line 58: 220
        line 64: 223
      LocalVariableTable:
        Start  Length  Slot  Name   Signature
            0     246     0  this   Larb/functions/real/factorℝ1;
            0     246     1    in   Larb/Integer;
            0     246     2 order   I
            0     246     3  bits   I
            0     246     4 result   Larb/Real;
           26     220     5 var10000   Larb/Real;
          138     108     6 var10001   Larb/Integer;
      StackMapTable: number_of_entries = 3
        frame_type = 11 /* same */
        frame_type = 252 /* append */
          offset_delta = 54
          locals = [ class arb/Real ]
        frame_type = 252 /* append */
          offset_delta = 111
          locals = [ class arb/Integer ]

[32m  public arb.functions.real.factorℝ1();[m
    descriptor: ()V
    flags: (0x0001) ACC_PUBLIC
[36m    Code:[m
      stack=4, locals=1, args_size=1
[33m         0:[m aload_0
[33m         1:[m invokespecial #140                [31m// Method java/lang/Object."<init>":()V[m
[33m         4:[m aload_0
[33m         5:[m new           #55                 [31m// class arb/functions/real/factorℝ2[m
[33m         8:[m dup
[33m         9:[m invokespecial #142                [31m// Method arb/functions/real/factorℝ2."<init>":()V[m
[33m        12:[m putfield      #52                 [31m// Field factorℝ2:Larb/functions/real/factorℝ2;[m
[33m        15:[m aload_0
[33m        16:[m new           #110                [31m// class arb/functions/real/factorℝ3[m
[33m        19:[m dup
[33m        20:[m invokespecial #143                [31m// Method arb/functions/real/factorℝ3."<init>":()V[m
[33m        23:[m putfield      #107                [31m// Field factorℝ3:Larb/functions/real/factorℝ3;[m
[33m        26:[m aload_0
[33m        27:[m new           #70                 [31m// class arb/Integer[m
[33m        30:[m dup
[33m        31:[m ldc           #144                [31m// String 1[m
[33m        33:[m invokespecial #146                [31m// Method arb/Integer."<init>":(Ljava/lang/String;)V[m
[33m        36:[m putfield      #67                 [31m// Field c1:Larb/Integer;[m
[33m        39:[m aload_0
[33m        40:[m new           #47                 [31m// class arb/Real[m
[33m        43:[m dup
[33m        44:[m invokespecial #149                [31m// Method arb/Real."<init>":()V[m
[33m        47:[m putfield      #44                 [31m// Field ℝ1:Larb/Real;[m
[33m        50:[m aload_0
[33m        51:[m new           #47                 [31m// class arb/Real[m
[33m        54:[m dup
[33m        55:[m invokespecial #149                [31m// Method arb/Real."<init>":()V[m
[33m        58:[m putfield      #79                 [31m// Field valueℝ2:Larb/Real;[m
[33m        61:[m aload_0
[33m        62:[m new           #70                 [31m// class arb/Integer[m
[33m        65:[m dup
[33m        66:[m invokespecial #150                [31m// Method arb/Integer."<init>":()V[m
[33m        69:[m putfield      #65                 [31m// Field k:Larb/Integer;[m
[33m        72:[m aload_0
[33m        73:[m new           #47                 [31m// class arb/Real[m
[33m        76:[m dup
[33m        77:[m invokespecial #149                [31m// Method arb/Real."<init>":()V[m
[33m        80:[m putfield      #59                 [31m// Field prodℝ1:Larb/Real;[m
[33m        83:[m aload_0
[33m        84:[m new           #70                 [31m// class arb/Integer[m
[33m        87:[m dup
[33m        88:[m invokespecial #150                [31m// Method arb/Integer."<init>":()V[m
[33m        91:[m putfield      #75                 [31m// Field endIndexℤ1:Larb/Integer;[m
[33m        94:[m aload_0
[33m        95:[m new           #47                 [31m// class arb/Real[m
[33m        98:[m dup
[33m        99:[m invokespecial #149                [31m// Method arb/Real."<init>":()V[m
[33m       102:[m putfield      #96                 [31m// Field ℝ2:Larb/Real;[m
[33m       105:[m aload_0
[33m       106:[m new           #70                 [31m// class arb/Integer[m
[33m       109:[m dup
[33m       110:[m invokespecial #150                [31m// Method arb/Integer."<init>":()V[m
[33m       113:[m putfield      #101                [31m// Field ℤ1:Larb/Integer;[m
[33m       116:[m aload_0
[33m       117:[m new           #47                 [31m// class arb/Real[m
[33m       120:[m dup
[33m       121:[m invokespecial #149                [31m// Method arb/Real."<init>":()V[m
[33m       124:[m putfield      #118                [31m// Field valueℝ3:Larb/Real;[m
[33m       127:[m aload_0
[33m       128:[m new           #47                 [31m// class arb/Real[m
[33m       131:[m dup
[33m       132:[m invokespecial #149                [31m// Method arb/Real."<init>":()V[m
[33m       135:[m putfield      #112                [31m// Field prodℝ2:Larb/Real;[m
[33m       138:[m aload_0
[33m       139:[m new           #70                 [31m// class arb/Integer[m
[33m       142:[m dup
[33m       143:[m invokespecial #150                [31m// Method arb/Integer."<init>":()V[m
[33m       146:[m putfield      #114                [31m// Field endIndexℤ2:Larb/Integer;[m
[33m       149:[m aload_0
[33m       150:[m new           #47                 [31m// class arb/Real[m
[33m       153:[m dup
[33m       154:[m invokespecial #149                [31m// Method arb/Real."<init>":()V[m
[33m       157:[m putfield      #121                [31m// Field ℝ3:Larb/Real;[m
[33m       160:[m return
      LineNumberTable:
        line 67: 0
        line 29: 4
        line 30: 15
        line 69: 26
        line 70: 39
        line 71: 50
        line 72: 61
        line 73: 72
        line 74: 83
        line 75: 94
        line 76: 105
        line 77: 116
        line 78: 127
        line 79: 138
        line 80: 149
        line 81: 160
      LocalVariableTable:
        Start  Length  Slot  Name   Signature
            0     161     0  this   Larb/functions/real/factorℝ1;

[32m  public void initialize();[m
    descriptor: ()V
    flags: (0x0001) ACC_PUBLIC
[36m    Code:[m
      stack=3, locals=1, args_size=1
[33m         0:[m aload_0
[33m         1:[m getfield      #36                 [31m// Field isInitialized:Z[m
[33m         4:[m ifeq          17
[33m         7:[m new           #151                [31m// class java/lang/AssertionError[m
[33m        10:[m dup
[33m        11:[m ldc           #153                [31m// String Already initialized[m
[33m        13:[m invokespecial #155                [31m// Method java/lang/AssertionError."<init>":(Ljava/lang/Object;)V[m
[33m        16:[m athrow
[33m        17:[m aload_0
[33m        18:[m getfield      #77                 [31m// Field p:Larb/Integer;[m
[33m        21:[m ifnonnull     34
[33m        24:[m new           #151                [31m// class java/lang/AssertionError[m
[33m        27:[m dup
[33m        28:[m ldc           #158                [31m// String p is null[m
[33m        30:[m invokespecial #155                [31m// Method java/lang/AssertionError."<init>":(Ljava/lang/Object;)V[m
[33m        33:[m athrow
[33m        34:[m aload_0
[33m        35:[m getfield      #116                [31m// Field q:Larb/Integer;[m
[33m        38:[m ifnonnull     51
[33m        41:[m new           #151                [31m// class java/lang/AssertionError[m
[33m        44:[m dup
[33m        45:[m ldc           #160                [31m// String q is null[m
[33m        47:[m invokespecial #155                [31m// Method java/lang/AssertionError."<init>":(Ljava/lang/Object;)V[m
[33m        50:[m athrow
[33m        51:[m aload_0
[33m        52:[m getfield      #52                 [31m// Field factorℝ2:Larb/functions/real/factorℝ2;[m
[33m        55:[m aload_0
[33m        56:[m getfield      #77                 [31m// Field p:Larb/Integer;[m
[33m        59:[m putfield      #162                [31m// Field arb/functions/real/factorℝ2.p:Larb/Integer;[m
[33m        62:[m aload_0
[33m        63:[m getfield      #52                 [31m// Field factorℝ2:Larb/functions/real/factorℝ2;[m
[33m        66:[m aload_0
[33m        67:[m getfield      #116                [31m// Field q:Larb/Integer;[m
[33m        70:[m putfield      #163                [31m// Field arb/functions/real/factorℝ2.q:Larb/Integer;[m
[33m        73:[m aload_0
[33m        74:[m getfield      #52                 [31m// Field factorℝ2:Larb/functions/real/factorℝ2;[m
[33m        77:[m aload_0
[33m        78:[m getfield      #164                [31m// Field α:Larb/Real;[m
[33m        81:[m putfield      #166                [31m// Field arb/functions/real/factorℝ2.α:Larb/Real;[m
[33m        84:[m aload_0
[33m        85:[m getfield      #52                 [31m// Field factorℝ2:Larb/functions/real/factorℝ2;[m
[33m        88:[m aload_0
[33m        89:[m getfield      #167                [31m// Field β:Larb/Real;[m
[33m        92:[m putfield      #169                [31m// Field arb/functions/real/factorℝ2.β:Larb/Real;[m
[33m        95:[m aload_0
[33m        96:[m getfield      #52                 [31m// Field factorℝ2:Larb/functions/real/factorℝ2;[m
[33m        99:[m aload_0
[33m       100:[m getfield      #170                [31m// Field N:Larb/Integer;[m
[33m       103:[m putfield      #172                [31m// Field arb/functions/real/factorℝ2.N:Larb/Integer;[m
[33m       106:[m aload_0
[33m       107:[m getfield      #107                [31m// Field factorℝ3:Larb/functions/real/factorℝ3;[m
[33m       110:[m aload_0
[33m       111:[m getfield      #77                 [31m// Field p:Larb/Integer;[m
[33m       114:[m putfield      #173                [31m// Field arb/functions/real/factorℝ3.p:Larb/Integer;[m
[33m       117:[m aload_0
[33m       118:[m getfield      #107                [31m// Field factorℝ3:Larb/functions/real/factorℝ3;[m
[33m       121:[m aload_0
[33m       122:[m getfield      #116                [31m// Field q:Larb/Integer;[m
[33m       125:[m putfield      #174                [31m// Field arb/functions/real/factorℝ3.q:Larb/Integer;[m
[33m       128:[m aload_0
[33m       129:[m getfield      #107                [31m// Field factorℝ3:Larb/functions/real/factorℝ3;[m
[33m       132:[m aload_0
[33m       133:[m getfield      #164                [31m// Field α:Larb/Real;[m
[33m       136:[m putfield      #175                [31m// Field arb/functions/real/factorℝ3.α:Larb/Real;[m
[33m       139:[m aload_0
[33m       140:[m getfield      #107                [31m// Field factorℝ3:Larb/functions/real/factorℝ3;[m
[33m       143:[m aload_0
[33m       144:[m getfield      #167                [31m// Field β:Larb/Real;[m
[33m       147:[m putfield      #176                [31m// Field arb/functions/real/factorℝ3.β:Larb/Real;[m
[33m       150:[m aload_0
[33m       151:[m getfield      #107                [31m// Field factorℝ3:Larb/functions/real/factorℝ3;[m
[33m       154:[m aload_0
[33m       155:[m getfield      #170                [31m// Field N:Larb/Integer;[m
[33m       158:[m putfield      #177                [31m// Field arb/functions/real/factorℝ3.N:Larb/Integer;[m
[33m       161:[m aload_0
[33m       162:[m iconst_1
[33m       163:[m putfield      #36                 [31m// Field isInitialized:Z[m
[33m       166:[m return
      LineNumberTable:
        line 85: 0
        line 87: 7
        line 89: 17
        line 91: 24
        line 93: 34
        line 95: 41
        line 99: 51
        line 100: 62
        line 101: 73
        line 102: 84
        line 103: 95
        line 104: 106
        line 105: 117
        line 106: 128
        line 107: 139
        line 108: 150
        line 109: 161
        line 111: 166
      LocalVariableTable:
        Start  Length  Slot  Name   Signature
            0     167     0  this   Larb/functions/real/factorℝ1;
      StackMapTable: number_of_entries = 3
        frame_type = 17 /* same */
        frame_type = 16 /* same */
        frame_type = 16 /* same */

[32m  public void close();[m
    descriptor: ()V
    flags: (0x0001) ACC_PUBLIC
[36m    Code:[m
      stack=1, locals=1, args_size=1
[33m         0:[m aload_0
[33m         1:[m getfield      #67                 [31m// Field c1:Larb/Integer;[m
[33m         4:[m invokevirtual #179                [31m// Method arb/Integer.close:()V[m
[33m         7:[m aload_0
[33m         8:[m getfield      #44                 [31m// Field ℝ1:Larb/Real;[m
[33m        11:[m invokevirtual #181                [31m// Method arb/Real.close:()V[m
[33m        14:[m aload_0
[33m        15:[m getfield      #79                 [31m// Field valueℝ2:Larb/Real;[m
[33m        18:[m invokevirtual #181                [31m// Method arb/Real.close:()V[m
[33m        21:[m aload_0
[33m        22:[m getfield      #65                 [31m// Field k:Larb/Integer;[m
[33m        25:[m invokevirtual #179                [31m// Method arb/Integer.close:()V[m
[33m        28:[m aload_0
[33m        29:[m getfield      #59                 [31m// Field prodℝ1:Larb/Real;[m
[33m        32:[m invokevirtual #181                [31m// Method arb/Real.close:()V[m
[33m        35:[m aload_0
[33m        36:[m getfield      #75                 [31m// Field endIndexℤ1:Larb/Integer;[m
[33m        39:[m invokevirtual #179                [31m// Method arb/Integer.close:()V[m
[33m        42:[m aload_0
[33m        43:[m getfield      #96                 [31m// Field ℝ2:Larb/Real;[m
[33m        46:[m invokevirtual #181                [31m// Method arb/Real.close:()V[m
[33m        49:[m aload_0
[33m        50:[m getfield      #101                [31m// Field ℤ1:Larb/Integer;[m
[33m        53:[m invokevirtual #179                [31m// Method arb/Integer.close:()V[m
[33m        56:[m aload_0
[33m        57:[m getfield      #118                [31m// Field valueℝ3:Larb/Real;[m
[33m        60:[m invokevirtual #181                [31m// Method arb/Real.close:()V[m
[33m        63:[m aload_0
[33m        64:[m getfield      #112                [31m// Field prodℝ2:Larb/Real;[m
[33m        67:[m invokevirtual #181                [31m// Method arb/Real.close:()V[m
[33m        70:[m aload_0
[33m        71:[m getfield      #114                [31m// Field endIndexℤ2:Larb/Integer;[m
[33m        74:[m invokevirtual #179                [31m// Method arb/Integer.close:()V[m
[33m        77:[m aload_0
[33m        78:[m getfield      #121                [31m// Field ℝ3:Larb/Real;[m
[33m        81:[m invokevirtual #181                [31m// Method arb/Real.close:()V[m
[33m        84:[m return
      LineNumberTable:
        line 115: 0
        line 116: 7
        line 117: 14
        line 118: 21
        line 119: 28
        line 120: 35
        line 121: 42
        line 122: 49
        line 123: 56
        line 124: 63
        line 125: 70
        line 126: 77
        line 127: 84
      LocalVariableTable:
        Start  Length  Slot  Name   Signature
            0      85     0  this   Larb/functions/real/factorℝ1;

[32m  public java.lang.Object evaluate(java.lang.Object, int, int, java.lang.Object);[m
    descriptor: (Ljava/lang/Object;IILjava/lang/Object;)Ljava/lang/Object;
    flags: (0x1041) ACC_PUBLIC, ACC_BRIDGE, ACC_SYNTHETIC
[36m    Code:[m
      stack=5, locals=5, args_size=5
[33m         0:[m aload_0
[33m         1:[m aload_1
[33m         2:[m checkcast     #70                 [31m// class arb/Integer[m
[33m         5:[m iload_2
[33m         6:[m iload_3
[33m         7:[m aload         4
[33m         9:[m checkcast     #47                 [31m// class arb/Real[m
[33m        12:[m invokevirtual #183                [31m// Method evaluate:(Larb/Integer;IILarb/Real;)Larb/Real;[m
[33m        15:[m areturn
      LineNumberTable:
        line 1: 0
      LocalVariableTable:
        Start  Length  Slot  Name   Signature
}
SourceFile: "factorℝ1.java"
Signature: #188                         [31m// Ljava/lang/Object;Larb/functions/Function<Larb/Integer;Larb/Real;>;[m
