\documentclass{article}
\usepackage{amsmath}
\usepackage[margin=1in]{geometry}
\title{Bytecode Analysis of \texttt{evaluate} Method with Stack States and Type Information}
\begin{document}
\maketitle

\textbf{Method Signature:} \\
\texttt{public arb.Real evaluate(java.lang.Void, int, int, arb.Real);}

\begin{verbatim}
0: aload_0                    // Stack: [this:arb.Real]
1: getfield #13               // Stack: [Real:arb.Real]  Field ℝ1:Larb/Real;
4: aload_0                    // Stack: [Real:arb.Real, this:arb.Real]
5: getfield #14               // Stack: [Real:arb.Real, Real:arb.Real] Field arb/functions/real/NullaryFunction.ℝ1:Larb/Real;
8: invokevirtual #20          // Stack: [Real:arb.Real] Method arb/Real.one:()Larb/Real;
11: pop                        // Stack: []
12: aload_0                    // Stack: [this:arb.Real]
13: getfield #24               // Stack: [Integer:arb.Integer] Field arb/functions/real/NullaryFunction.k:Larb/Integer;
16: aload_0                    // Stack: [Integer:arb.Integer, this:arb.Real]
17: getfield #27               // Stack: [Integer:arb.Integer, Integer:arb.Integer] Field arb/functions/real/NullaryFunction.startIndex:Larb/Integer;
20: invokevirtual #33          // Stack: [] Method arb/Integer.set:(Larb/Integer;)Larb/Integer;
23: pop                        // Stack: []
24: goto 52                    // Jump to instruction at index 52; Stack state unchanged
27: aload_0                    // Stack: [this:arb.Real]
28: getfield #14               // Stack: [Real:arb.Real] Field arb/functions/real/NullaryFunction.ℝ1:Larb/Real;
31: aload_1                    // Stack: [Real:arb.Real, Void:java.lang.Void]
32: checkcast #35              // Stack: [Real:arb.Real, Void:java.lang.Void] class java/lang/Void
35: iload_1                    // Stack: [Real:arb.Real, Void:java.lang.Void, int]
36: aload_0                    // Stack: [Real:arb.Real, Void:java.lang.Void, int, this:arb.Real]
37: getfield #14               // Stack: [Real:arb.Real, Void:java.lang.Void, int, Real:arb.Real] Field arb/functions/real/NullaryFunction.ℝ1:Larb/Real;
40: invokevirtual #39          // Stack: [] Method arb/Real.mul:(Larb/Real;ILarb/Real;)Larb/Real;
43: pop                        // Stack: []
44: aload_0                    // Stack: [this:arb.Real]
45: getfield #24               // Stack: [Integer:arb.Integer] Field arb/functions/real/NullaryFunction.k:Larb/Integer;
48: invokevirtual #43          // Stack: [] Method arb/Integer.increment:()Larb/Integer;
51: pop                        // Stack: []
52: aload_0                    // Stack: [this:arb.Real]
53: getfield #24               // Stack: [Integer:arb.Integer] Field arb/functions/real/NullaryFunction.k:Larb/Integer;
56: aload_0                    // Stack: [Integer:arb.Integer, this:arb.Real]
57: getfield #46               // Stack: [Integer:arb.Integer, Integer:arb.Integer] Field arb/functions/real/NullaryFunction.endIndex:Larb/Integer;
60: invokevirtual #50          // Stack: [int] Method arb/Integer.compareTo:(Larb/Integer;)I
63: ifle 27                    // Conditional jump based on comparison result
66: areturn                    // Return from the method
\end{verbatim}

\end{document}
